djangocms_pai_bootstrap3/__init__.py
djangocms_pai_bootstrap3/apps.py
djangocms_pai_bootstrap3/templates/djangocms_pai_bootstrap3/base.html
djangocms_pai_bootstrap3-0.0.1.dist-info/AUTHORS.rst
djangocms_pai_bootstrap3-0.0.1.dist-info/LICENSE.txt
djangocms_pai_bootstrap3-0.0.1.dist-info/METADATA
djangocms_pai_bootstrap3-0.0.1.dist-info/WHEEL
djangocms_pai_bootstrap3-0.0.1.dist-info/top_level.txt
djangocms_pai_bootstrap3-0.0.1.dist-info/RECORD
