Metadata-Version: 2.1
Name: djangocms-pai-bootstrap3
Version: 0.0.1
Summary: Django-cms Bootstrap3 template app
Home-page: https://bitbucket.org/pai/djangocms-pai-bootstrap3
Author: pai
Author-email: paiuolo@gmail.com
License: mit
Platform: any
Classifier: Development Status :: 4 - Beta
Classifier: Programming Language :: Python
Provides-Extra: testing
Requires-Dist: pytest ; extra == 'testing'
Requires-Dist: pytest-cov ; extra == 'testing'
